{
	"artifacts" : 
	[
		{
			"path" : "/home/dev/sylar/lib/libjujimeizuo.so"
		}
	],
	"backtrace" : 1,
	"backtraceGraph" : 
	{
		"commands" : 
		[
			"add_library",
			"include_directories",
			"set_property",
			"force_redefine_file_macro_for_sources"
		],
		"files" : 
		[
			"CMakeLists.txt",
			"cmake/utils.cmake"
		],
		"nodes" : 
		[
			{
				"file" : 0
			},
			{
				"command" : 0,
				"file" : 0,
				"line" : 60,
				"parent" : 0
			},
			{
				"command" : 1,
				"file" : 0,
				"line" : 21,
				"parent" : 0
			},
			{
				"command" : 3,
				"file" : 0,
				"line" : 61,
				"parent" : 0
			},
			{
				"command" : 2,
				"file" : 1,
				"line" : 19,
				"parent" : 3
			},
			{
				"command" : 2,
				"file" : 1,
				"line" : 19,
				"parent" : 3
			},
			{
				"command" : 2,
				"file" : 1,
				"line" : 19,
				"parent" : 3
			},
			{
				"command" : 2,
				"file" : 1,
				"line" : 19,
				"parent" : 3
			},
			{
				"command" : 2,
				"file" : 1,
				"line" : 19,
				"parent" : 3
			},
			{
				"command" : 2,
				"file" : 1,
				"line" : 19,
				"parent" : 3
			},
			{
				"command" : 2,
				"file" : 1,
				"line" : 19,
				"parent" : 3
			},
			{
				"command" : 2,
				"file" : 1,
				"line" : 19,
				"parent" : 3
			},
			{
				"command" : 2,
				"file" : 1,
				"line" : 19,
				"parent" : 3
			},
			{
				"command" : 2,
				"file" : 1,
				"line" : 19,
				"parent" : 3
			},
			{
				"command" : 2,
				"file" : 1,
				"line" : 19,
				"parent" : 3
			},
			{
				"command" : 2,
				"file" : 1,
				"line" : 19,
				"parent" : 3
			},
			{
				"command" : 2,
				"file" : 1,
				"line" : 19,
				"parent" : 3
			},
			{
				"command" : 2,
				"file" : 1,
				"line" : 19,
				"parent" : 3
			},
			{
				"command" : 2,
				"file" : 1,
				"line" : 19,
				"parent" : 3
			},
			{
				"command" : 2,
				"file" : 1,
				"line" : 19,
				"parent" : 3
			},
			{
				"command" : 2,
				"file" : 1,
				"line" : 19,
				"parent" : 3
			},
			{
				"command" : 2,
				"file" : 1,
				"line" : 19,
				"parent" : 3
			},
			{
				"command" : 2,
				"file" : 1,
				"line" : 19,
				"parent" : 3
			},
			{
				"command" : 2,
				"file" : 1,
				"line" : 19,
				"parent" : 3
			},
			{
				"command" : 2,
				"file" : 1,
				"line" : 19,
				"parent" : 3
			},
			{
				"command" : 2,
				"file" : 1,
				"line" : 19,
				"parent" : 3
			},
			{
				"command" : 2,
				"file" : 1,
				"line" : 19,
				"parent" : 3
			},
			{
				"command" : 2,
				"file" : 1,
				"line" : 19,
				"parent" : 3
			},
			{
				"command" : 2,
				"file" : 1,
				"line" : 19,
				"parent" : 3
			},
			{
				"command" : 2,
				"file" : 1,
				"line" : 19,
				"parent" : 3
			},
			{
				"command" : 2,
				"file" : 1,
				"line" : 19,
				"parent" : 3
			}
		]
	},
	"compileGroups" : 
	[
		{
			"compileCommandFragments" : 
			[
				{
					"fragment" : " -std=c++11 -O0 -ggdb -Wall -Werror -rdynamic -fPIC -Wno-unused-function -Wno-builtin-macro-redefined -Wno-deprecated -Wno-deprecated-declarations -fPIC"
				}
			],
			"defines" : 
			[
				{
					"backtrace" : 4,
					"define" : "__FILE__=\"jujimeizuo/log.cpp\""
				},
				{
					"define" : "jujimeizuo_EXPORTS"
				}
			],
			"includes" : 
			[
				{
					"backtrace" : 2,
					"path" : "/home/dev/sylar/."
				}
			],
			"language" : "CXX",
			"sourceIndexes" : 
			[
				0
			]
		},
		{
			"compileCommandFragments" : 
			[
				{
					"fragment" : " -std=c++11 -O0 -ggdb -Wall -Werror -rdynamic -fPIC -Wno-unused-function -Wno-builtin-macro-redefined -Wno-deprecated -Wno-deprecated-declarations -fPIC"
				}
			],
			"defines" : 
			[
				{
					"backtrace" : 5,
					"define" : "__FILE__=\"jujimeizuo/util.cpp\""
				},
				{
					"define" : "jujimeizuo_EXPORTS"
				}
			],
			"includes" : 
			[
				{
					"backtrace" : 2,
					"path" : "/home/dev/sylar/."
				}
			],
			"language" : "CXX",
			"sourceIndexes" : 
			[
				1
			]
		},
		{
			"compileCommandFragments" : 
			[
				{
					"fragment" : " -std=c++11 -O0 -ggdb -Wall -Werror -rdynamic -fPIC -Wno-unused-function -Wno-builtin-macro-redefined -Wno-deprecated -Wno-deprecated-declarations -fPIC"
				}
			],
			"defines" : 
			[
				{
					"backtrace" : 6,
					"define" : "__FILE__=\"jujimeizuo/mutex.cc\""
				},
				{
					"define" : "jujimeizuo_EXPORTS"
				}
			],
			"includes" : 
			[
				{
					"backtrace" : 2,
					"path" : "/home/dev/sylar/."
				}
			],
			"language" : "CXX",
			"sourceIndexes" : 
			[
				2
			]
		},
		{
			"compileCommandFragments" : 
			[
				{
					"fragment" : " -std=c++11 -O0 -ggdb -Wall -Werror -rdynamic -fPIC -Wno-unused-function -Wno-builtin-macro-redefined -Wno-deprecated -Wno-deprecated-declarations -fPIC"
				}
			],
			"defines" : 
			[
				{
					"backtrace" : 7,
					"define" : "__FILE__=\"jujimeizuo/env.cc\""
				},
				{
					"define" : "jujimeizuo_EXPORTS"
				}
			],
			"includes" : 
			[
				{
					"backtrace" : 2,
					"path" : "/home/dev/sylar/."
				}
			],
			"language" : "CXX",
			"sourceIndexes" : 
			[
				3
			]
		},
		{
			"compileCommandFragments" : 
			[
				{
					"fragment" : " -std=c++11 -O0 -ggdb -Wall -Werror -rdynamic -fPIC -Wno-unused-function -Wno-builtin-macro-redefined -Wno-deprecated -Wno-deprecated-declarations -fPIC"
				}
			],
			"defines" : 
			[
				{
					"backtrace" : 8,
					"define" : "__FILE__=\"jujimeizuo/config.cc\""
				},
				{
					"define" : "jujimeizuo_EXPORTS"
				}
			],
			"includes" : 
			[
				{
					"backtrace" : 2,
					"path" : "/home/dev/sylar/."
				}
			],
			"language" : "CXX",
			"sourceIndexes" : 
			[
				4
			]
		},
		{
			"compileCommandFragments" : 
			[
				{
					"fragment" : " -std=c++11 -O0 -ggdb -Wall -Werror -rdynamic -fPIC -Wno-unused-function -Wno-builtin-macro-redefined -Wno-deprecated -Wno-deprecated-declarations -fPIC"
				}
			],
			"defines" : 
			[
				{
					"backtrace" : 9,
					"define" : "__FILE__=\"jujimeizuo/thread.cc\""
				},
				{
					"define" : "jujimeizuo_EXPORTS"
				}
			],
			"includes" : 
			[
				{
					"backtrace" : 2,
					"path" : "/home/dev/sylar/."
				}
			],
			"language" : "CXX",
			"sourceIndexes" : 
			[
				5
			]
		},
		{
			"compileCommandFragments" : 
			[
				{
					"fragment" : " -std=c++11 -O0 -ggdb -Wall -Werror -rdynamic -fPIC -Wno-unused-function -Wno-builtin-macro-redefined -Wno-deprecated -Wno-deprecated-declarations -fPIC"
				}
			],
			"defines" : 
			[
				{
					"backtrace" : 10,
					"define" : "__FILE__=\"jujimeizuo/fiber.cc\""
				},
				{
					"define" : "jujimeizuo_EXPORTS"
				}
			],
			"includes" : 
			[
				{
					"backtrace" : 2,
					"path" : "/home/dev/sylar/."
				}
			],
			"language" : "CXX",
			"sourceIndexes" : 
			[
				6
			]
		},
		{
			"compileCommandFragments" : 
			[
				{
					"fragment" : " -std=c++11 -O0 -ggdb -Wall -Werror -rdynamic -fPIC -Wno-unused-function -Wno-builtin-macro-redefined -Wno-deprecated -Wno-deprecated-declarations -fPIC"
				}
			],
			"defines" : 
			[
				{
					"backtrace" : 11,
					"define" : "__FILE__=\"jujimeizuo/scheduler.cc\""
				},
				{
					"define" : "jujimeizuo_EXPORTS"
				}
			],
			"includes" : 
			[
				{
					"backtrace" : 2,
					"path" : "/home/dev/sylar/."
				}
			],
			"language" : "CXX",
			"sourceIndexes" : 
			[
				7
			]
		},
		{
			"compileCommandFragments" : 
			[
				{
					"fragment" : " -std=c++11 -O0 -ggdb -Wall -Werror -rdynamic -fPIC -Wno-unused-function -Wno-builtin-macro-redefined -Wno-deprecated -Wno-deprecated-declarations -fPIC"
				}
			],
			"defines" : 
			[
				{
					"backtrace" : 12,
					"define" : "__FILE__=\"jujimeizuo/iomanager.cc\""
				},
				{
					"define" : "jujimeizuo_EXPORTS"
				}
			],
			"includes" : 
			[
				{
					"backtrace" : 2,
					"path" : "/home/dev/sylar/."
				}
			],
			"language" : "CXX",
			"sourceIndexes" : 
			[
				8
			]
		},
		{
			"compileCommandFragments" : 
			[
				{
					"fragment" : " -std=c++11 -O0 -ggdb -Wall -Werror -rdynamic -fPIC -Wno-unused-function -Wno-builtin-macro-redefined -Wno-deprecated -Wno-deprecated-declarations -fPIC"
				}
			],
			"defines" : 
			[
				{
					"backtrace" : 13,
					"define" : "__FILE__=\"jujimeizuo/timer.cc\""
				},
				{
					"define" : "jujimeizuo_EXPORTS"
				}
			],
			"includes" : 
			[
				{
					"backtrace" : 2,
					"path" : "/home/dev/sylar/."
				}
			],
			"language" : "CXX",
			"sourceIndexes" : 
			[
				9
			]
		},
		{
			"compileCommandFragments" : 
			[
				{
					"fragment" : " -std=c++11 -O0 -ggdb -Wall -Werror -rdynamic -fPIC -Wno-unused-function -Wno-builtin-macro-redefined -Wno-deprecated -Wno-deprecated-declarations -fPIC"
				}
			],
			"defines" : 
			[
				{
					"backtrace" : 14,
					"define" : "__FILE__=\"jujimeizuo/fd_manager.cc\""
				},
				{
					"define" : "jujimeizuo_EXPORTS"
				}
			],
			"includes" : 
			[
				{
					"backtrace" : 2,
					"path" : "/home/dev/sylar/."
				}
			],
			"language" : "CXX",
			"sourceIndexes" : 
			[
				10
			]
		},
		{
			"compileCommandFragments" : 
			[
				{
					"fragment" : " -std=c++11 -O0 -ggdb -Wall -Werror -rdynamic -fPIC -Wno-unused-function -Wno-builtin-macro-redefined -Wno-deprecated -Wno-deprecated-declarations -fPIC"
				}
			],
			"defines" : 
			[
				{
					"backtrace" : 15,
					"define" : "__FILE__=\"jujimeizuo/hook.cc\""
				},
				{
					"define" : "jujimeizuo_EXPORTS"
				}
			],
			"includes" : 
			[
				{
					"backtrace" : 2,
					"path" : "/home/dev/sylar/."
				}
			],
			"language" : "CXX",
			"sourceIndexes" : 
			[
				11
			]
		},
		{
			"compileCommandFragments" : 
			[
				{
					"fragment" : " -std=c++11 -O0 -ggdb -Wall -Werror -rdynamic -fPIC -Wno-unused-function -Wno-builtin-macro-redefined -Wno-deprecated -Wno-deprecated-declarations -fPIC"
				}
			],
			"defines" : 
			[
				{
					"backtrace" : 16,
					"define" : "__FILE__=\"jujimeizuo/address.cc\""
				},
				{
					"define" : "jujimeizuo_EXPORTS"
				}
			],
			"includes" : 
			[
				{
					"backtrace" : 2,
					"path" : "/home/dev/sylar/."
				}
			],
			"language" : "CXX",
			"sourceIndexes" : 
			[
				12
			]
		},
		{
			"compileCommandFragments" : 
			[
				{
					"fragment" : " -std=c++11 -O0 -ggdb -Wall -Werror -rdynamic -fPIC -Wno-unused-function -Wno-builtin-macro-redefined -Wno-deprecated -Wno-deprecated-declarations -fPIC"
				}
			],
			"defines" : 
			[
				{
					"backtrace" : 17,
					"define" : "__FILE__=\"jujimeizuo/socket.cc\""
				},
				{
					"define" : "jujimeizuo_EXPORTS"
				}
			],
			"includes" : 
			[
				{
					"backtrace" : 2,
					"path" : "/home/dev/sylar/."
				}
			],
			"language" : "CXX",
			"sourceIndexes" : 
			[
				13
			]
		},
		{
			"compileCommandFragments" : 
			[
				{
					"fragment" : " -std=c++11 -O0 -ggdb -Wall -Werror -rdynamic -fPIC -Wno-unused-function -Wno-builtin-macro-redefined -Wno-deprecated -Wno-deprecated-declarations -fPIC"
				}
			],
			"defines" : 
			[
				{
					"backtrace" : 18,
					"define" : "__FILE__=\"jujimeizuo/bytearray.cc\""
				},
				{
					"define" : "jujimeizuo_EXPORTS"
				}
			],
			"includes" : 
			[
				{
					"backtrace" : 2,
					"path" : "/home/dev/sylar/."
				}
			],
			"language" : "CXX",
			"sourceIndexes" : 
			[
				14
			]
		},
		{
			"compileCommandFragments" : 
			[
				{
					"fragment" : " -std=c++11 -O0 -ggdb -Wall -Werror -rdynamic -fPIC -Wno-unused-function -Wno-builtin-macro-redefined -Wno-deprecated -Wno-deprecated-declarations -fPIC"
				}
			],
			"defines" : 
			[
				{
					"backtrace" : 19,
					"define" : "__FILE__=\"jujimeizuo/tcp_server.cc\""
				},
				{
					"define" : "jujimeizuo_EXPORTS"
				}
			],
			"includes" : 
			[
				{
					"backtrace" : 2,
					"path" : "/home/dev/sylar/."
				}
			],
			"language" : "CXX",
			"sourceIndexes" : 
			[
				15
			]
		},
		{
			"compileCommandFragments" : 
			[
				{
					"fragment" : "-fPIC"
				}
			],
			"defines" : 
			[
				{
					"backtrace" : 20,
					"define" : "__FILE__=\"jujimeizuo/http/http-parser/http_parser.c\""
				},
				{
					"define" : "jujimeizuo_EXPORTS"
				}
			],
			"includes" : 
			[
				{
					"backtrace" : 2,
					"path" : "/home/dev/sylar/."
				}
			],
			"language" : "C",
			"sourceIndexes" : 
			[
				16
			]
		},
		{
			"compileCommandFragments" : 
			[
				{
					"fragment" : " -std=c++11 -O0 -ggdb -Wall -Werror -rdynamic -fPIC -Wno-unused-function -Wno-builtin-macro-redefined -Wno-deprecated -Wno-deprecated-declarations -fPIC"
				}
			],
			"defines" : 
			[
				{
					"backtrace" : 21,
					"define" : "__FILE__=\"jujimeizuo/http/http.cc\""
				},
				{
					"define" : "jujimeizuo_EXPORTS"
				}
			],
			"includes" : 
			[
				{
					"backtrace" : 2,
					"path" : "/home/dev/sylar/."
				}
			],
			"language" : "CXX",
			"sourceIndexes" : 
			[
				17
			]
		},
		{
			"compileCommandFragments" : 
			[
				{
					"fragment" : " -std=c++11 -O0 -ggdb -Wall -Werror -rdynamic -fPIC -Wno-unused-function -Wno-builtin-macro-redefined -Wno-deprecated -Wno-deprecated-declarations -fPIC"
				}
			],
			"defines" : 
			[
				{
					"backtrace" : 22,
					"define" : "__FILE__=\"jujimeizuo/http/http_parser.cc\""
				},
				{
					"define" : "jujimeizuo_EXPORTS"
				}
			],
			"includes" : 
			[
				{
					"backtrace" : 2,
					"path" : "/home/dev/sylar/."
				}
			],
			"language" : "CXX",
			"sourceIndexes" : 
			[
				18
			]
		},
		{
			"compileCommandFragments" : 
			[
				{
					"fragment" : " -std=c++11 -O0 -ggdb -Wall -Werror -rdynamic -fPIC -Wno-unused-function -Wno-builtin-macro-redefined -Wno-deprecated -Wno-deprecated-declarations -fPIC"
				}
			],
			"defines" : 
			[
				{
					"backtrace" : 23,
					"define" : "__FILE__=\"jujimeizuo/stream.cc\""
				},
				{
					"define" : "jujimeizuo_EXPORTS"
				}
			],
			"includes" : 
			[
				{
					"backtrace" : 2,
					"path" : "/home/dev/sylar/."
				}
			],
			"language" : "CXX",
			"sourceIndexes" : 
			[
				19
			]
		},
		{
			"compileCommandFragments" : 
			[
				{
					"fragment" : " -std=c++11 -O0 -ggdb -Wall -Werror -rdynamic -fPIC -Wno-unused-function -Wno-builtin-macro-redefined -Wno-deprecated -Wno-deprecated-declarations -fPIC"
				}
			],
			"defines" : 
			[
				{
					"backtrace" : 24,
					"define" : "__FILE__=\"jujimeizuo/streams/socket_stream.cc\""
				},
				{
					"define" : "jujimeizuo_EXPORTS"
				}
			],
			"includes" : 
			[
				{
					"backtrace" : 2,
					"path" : "/home/dev/sylar/."
				}
			],
			"language" : "CXX",
			"sourceIndexes" : 
			[
				20
			]
		},
		{
			"compileCommandFragments" : 
			[
				{
					"fragment" : " -std=c++11 -O0 -ggdb -Wall -Werror -rdynamic -fPIC -Wno-unused-function -Wno-builtin-macro-redefined -Wno-deprecated -Wno-deprecated-declarations -fPIC"
				}
			],
			"defines" : 
			[
				{
					"backtrace" : 25,
					"define" : "__FILE__=\"jujimeizuo/http/http_session.cc\""
				},
				{
					"define" : "jujimeizuo_EXPORTS"
				}
			],
			"includes" : 
			[
				{
					"backtrace" : 2,
					"path" : "/home/dev/sylar/."
				}
			],
			"language" : "CXX",
			"sourceIndexes" : 
			[
				21
			]
		},
		{
			"compileCommandFragments" : 
			[
				{
					"fragment" : " -std=c++11 -O0 -ggdb -Wall -Werror -rdynamic -fPIC -Wno-unused-function -Wno-builtin-macro-redefined -Wno-deprecated -Wno-deprecated-declarations -fPIC"
				}
			],
			"defines" : 
			[
				{
					"backtrace" : 26,
					"define" : "__FILE__=\"jujimeizuo/http/servlet.cc\""
				},
				{
					"define" : "jujimeizuo_EXPORTS"
				}
			],
			"includes" : 
			[
				{
					"backtrace" : 2,
					"path" : "/home/dev/sylar/."
				}
			],
			"language" : "CXX",
			"sourceIndexes" : 
			[
				22
			]
		},
		{
			"compileCommandFragments" : 
			[
				{
					"fragment" : " -std=c++11 -O0 -ggdb -Wall -Werror -rdynamic -fPIC -Wno-unused-function -Wno-builtin-macro-redefined -Wno-deprecated -Wno-deprecated-declarations -fPIC"
				}
			],
			"defines" : 
			[
				{
					"backtrace" : 27,
					"define" : "__FILE__=\"jujimeizuo/http/http_server.cc\""
				},
				{
					"define" : "jujimeizuo_EXPORTS"
				}
			],
			"includes" : 
			[
				{
					"backtrace" : 2,
					"path" : "/home/dev/sylar/."
				}
			],
			"language" : "CXX",
			"sourceIndexes" : 
			[
				23
			]
		},
		{
			"compileCommandFragments" : 
			[
				{
					"fragment" : " -std=c++11 -O0 -ggdb -Wall -Werror -rdynamic -fPIC -Wno-unused-function -Wno-builtin-macro-redefined -Wno-deprecated -Wno-deprecated-declarations -fPIC"
				}
			],
			"defines" : 
			[
				{
					"backtrace" : 28,
					"define" : "__FILE__=\"jujimeizuo/uri.cc\""
				},
				{
					"define" : "jujimeizuo_EXPORTS"
				}
			],
			"includes" : 
			[
				{
					"backtrace" : 2,
					"path" : "/home/dev/sylar/."
				}
			],
			"language" : "CXX",
			"sourceIndexes" : 
			[
				24
			]
		},
		{
			"compileCommandFragments" : 
			[
				{
					"fragment" : " -std=c++11 -O0 -ggdb -Wall -Werror -rdynamic -fPIC -Wno-unused-function -Wno-builtin-macro-redefined -Wno-deprecated -Wno-deprecated-declarations -fPIC"
				}
			],
			"defines" : 
			[
				{
					"backtrace" : 29,
					"define" : "__FILE__=\"jujimeizuo/http/http_connection.cc\""
				},
				{
					"define" : "jujimeizuo_EXPORTS"
				}
			],
			"includes" : 
			[
				{
					"backtrace" : 2,
					"path" : "/home/dev/sylar/."
				}
			],
			"language" : "CXX",
			"sourceIndexes" : 
			[
				25
			]
		},
		{
			"compileCommandFragments" : 
			[
				{
					"fragment" : " -std=c++11 -O0 -ggdb -Wall -Werror -rdynamic -fPIC -Wno-unused-function -Wno-builtin-macro-redefined -Wno-deprecated -Wno-deprecated-declarations -fPIC"
				}
			],
			"defines" : 
			[
				{
					"backtrace" : 30,
					"define" : "__FILE__=\"jujimeizuo/daemon.cc\""
				},
				{
					"define" : "jujimeizuo_EXPORTS"
				}
			],
			"includes" : 
			[
				{
					"backtrace" : 2,
					"path" : "/home/dev/sylar/."
				}
			],
			"language" : "CXX",
			"sourceIndexes" : 
			[
				26
			]
		}
	],
	"id" : "jujimeizuo::@6890427a1f51a3e7e1df",
	"link" : 
	{
		"commandFragments" : 
		[
			{
				"fragment" : "",
				"role" : "flags"
			}
		],
		"language" : "CXX"
	},
	"name" : "jujimeizuo",
	"nameOnDisk" : "libjujimeizuo.so",
	"paths" : 
	{
		"build" : ".",
		"source" : "."
	},
	"sourceGroups" : 
	[
		{
			"name" : "Source Files",
			"sourceIndexes" : 
			[
				0,
				1,
				2,
				3,
				4,
				5,
				6,
				7,
				8,
				9,
				10,
				11,
				12,
				13,
				14,
				15,
				16,
				17,
				18,
				19,
				20,
				21,
				22,
				23,
				24,
				25,
				26
			]
		}
	],
	"sources" : 
	[
		{
			"backtrace" : 1,
			"compileGroupIndex" : 0,
			"path" : "jujimeizuo/log.cpp",
			"sourceGroupIndex" : 0
		},
		{
			"backtrace" : 1,
			"compileGroupIndex" : 1,
			"path" : "jujimeizuo/util.cpp",
			"sourceGroupIndex" : 0
		},
		{
			"backtrace" : 1,
			"compileGroupIndex" : 2,
			"path" : "jujimeizuo/mutex.cc",
			"sourceGroupIndex" : 0
		},
		{
			"backtrace" : 1,
			"compileGroupIndex" : 3,
			"path" : "jujimeizuo/env.cc",
			"sourceGroupIndex" : 0
		},
		{
			"backtrace" : 1,
			"compileGroupIndex" : 4,
			"path" : "jujimeizuo/config.cc",
			"sourceGroupIndex" : 0
		},
		{
			"backtrace" : 1,
			"compileGroupIndex" : 5,
			"path" : "jujimeizuo/thread.cc",
			"sourceGroupIndex" : 0
		},
		{
			"backtrace" : 1,
			"compileGroupIndex" : 6,
			"path" : "jujimeizuo/fiber.cc",
			"sourceGroupIndex" : 0
		},
		{
			"backtrace" : 1,
			"compileGroupIndex" : 7,
			"path" : "jujimeizuo/scheduler.cc",
			"sourceGroupIndex" : 0
		},
		{
			"backtrace" : 1,
			"compileGroupIndex" : 8,
			"path" : "jujimeizuo/iomanager.cc",
			"sourceGroupIndex" : 0
		},
		{
			"backtrace" : 1,
			"compileGroupIndex" : 9,
			"path" : "jujimeizuo/timer.cc",
			"sourceGroupIndex" : 0
		},
		{
			"backtrace" : 1,
			"compileGroupIndex" : 10,
			"path" : "jujimeizuo/fd_manager.cc",
			"sourceGroupIndex" : 0
		},
		{
			"backtrace" : 1,
			"compileGroupIndex" : 11,
			"path" : "jujimeizuo/hook.cc",
			"sourceGroupIndex" : 0
		},
		{
			"backtrace" : 1,
			"compileGroupIndex" : 12,
			"path" : "jujimeizuo/address.cc",
			"sourceGroupIndex" : 0
		},
		{
			"backtrace" : 1,
			"compileGroupIndex" : 13,
			"path" : "jujimeizuo/socket.cc",
			"sourceGroupIndex" : 0
		},
		{
			"backtrace" : 1,
			"compileGroupIndex" : 14,
			"path" : "jujimeizuo/bytearray.cc",
			"sourceGroupIndex" : 0
		},
		{
			"backtrace" : 1,
			"compileGroupIndex" : 15,
			"path" : "jujimeizuo/tcp_server.cc",
			"sourceGroupIndex" : 0
		},
		{
			"backtrace" : 1,
			"compileGroupIndex" : 16,
			"path" : "jujimeizuo/http/http-parser/http_parser.c",
			"sourceGroupIndex" : 0
		},
		{
			"backtrace" : 1,
			"compileGroupIndex" : 17,
			"path" : "jujimeizuo/http/http.cc",
			"sourceGroupIndex" : 0
		},
		{
			"backtrace" : 1,
			"compileGroupIndex" : 18,
			"path" : "jujimeizuo/http/http_parser.cc",
			"sourceGroupIndex" : 0
		},
		{
			"backtrace" : 1,
			"compileGroupIndex" : 19,
			"path" : "jujimeizuo/stream.cc",
			"sourceGroupIndex" : 0
		},
		{
			"backtrace" : 1,
			"compileGroupIndex" : 20,
			"path" : "jujimeizuo/streams/socket_stream.cc",
			"sourceGroupIndex" : 0
		},
		{
			"backtrace" : 1,
			"compileGroupIndex" : 21,
			"path" : "jujimeizuo/http/http_session.cc",
			"sourceGroupIndex" : 0
		},
		{
			"backtrace" : 1,
			"compileGroupIndex" : 22,
			"path" : "jujimeizuo/http/servlet.cc",
			"sourceGroupIndex" : 0
		},
		{
			"backtrace" : 1,
			"compileGroupIndex" : 23,
			"path" : "jujimeizuo/http/http_server.cc",
			"sourceGroupIndex" : 0
		},
		{
			"backtrace" : 1,
			"compileGroupIndex" : 24,
			"path" : "jujimeizuo/uri.cc",
			"sourceGroupIndex" : 0
		},
		{
			"backtrace" : 1,
			"compileGroupIndex" : 25,
			"path" : "jujimeizuo/http/http_connection.cc",
			"sourceGroupIndex" : 0
		},
		{
			"backtrace" : 1,
			"compileGroupIndex" : 26,
			"path" : "jujimeizuo/daemon.cc",
			"sourceGroupIndex" : 0
		}
	],
	"type" : "SHARED_LIBRARY"
}
